tf2inventory/__init__.py
tf2inventory-1.0.8.dist-info/METADATA
tf2inventory-1.0.8.dist-info/WHEEL
tf2inventory-1.0.8.dist-info/entry_points.txt
tf2inventory-1.0.8.dist-info/top_level.txt
tf2inventory-1.0.8.dist-info/RECORD
